accounts/__init__.py
accounts/apps.py
accounts/authentication.py
accounts/defaults.py
accounts/forms.py
accounts/signals.py
accounts/tokens.py
accounts/urls.py
accounts/views.py
accounts/migrations/__init__.py
accounts/templates/accounts/activate.html
accounts/templates/accounts/change-password.html
accounts/templates/accounts/login.html
accounts/templates/accounts/profile.html
accounts/templates/accounts/reset-password-confirm.html
accounts/templates/accounts/reset-password-done.html
accounts/templates/accounts/reset-password.html
accounts/templates/accounts/signup.html
djacc-0.1.6.dist-info/LICENSE.txt
djacc-0.1.6.dist-info/METADATA
djacc-0.1.6.dist-info/WHEEL
djacc-0.1.6.dist-info/top_level.txt
djacc-0.1.6.dist-info/RECORD
