Metadata-Version: 2.1
Name: djacc
Version: 0.1.6
Summary: An extensible user-accounts application for Django
Home-page: https://github.com/ardevpk/djacc
Author: Abdul Rehman
Author-email: adnan1470369258@gmail.com
Project-URL: Bug Tracker, https://github.com/ardevpk/djacc/issues
Classifier: Development Status :: 5 - Production/Stable
Classifier: Environment :: Web Environment
Classifier: Framework :: Django
Classifier: Framework :: Django :: 3.1
Classifier: Framework :: Django :: 3.2
Classifier: Framework :: Django :: 4.0
Classifier: Intended Audience :: Developers
Classifier: License :: OSI Approved :: BSD License
Classifier: Operating System :: OS Independent
Classifier: Programming Language :: Python
Classifier: Topic :: Software Development :: Libraries :: Python Modules
Classifier: Programming Language :: Python
Classifier: Programming Language :: Python :: 3
Classifier: Programming Language :: Python :: 3.7
Classifier: Programming Language :: Python :: 3.8
Classifier: Programming Language :: Python :: 3.9
Classifier: Programming Language :: Python :: 3.10
Classifier: Topic :: Utilities
Requires-Python: >=3.7
License-File: LICENSE.txt
Requires-Dist: Django (>=3.8)
Requires-Dist: django-crispy-forms (>=1.14.0)
Requires-Dist: django-utils-six (>=2.0)
